compecon/__init__.py
compecon/basis.py
compecon/basisChebyshev.py
compecon/basisLinear.py
compecon/basisSpline.py
compecon/ce_util.py
compecon/chebyc.py
compecon/ddpmodel.py
compecon/deprecated.py
compecon/dpmodel.py
compecon/interpolator.py
compecon/interpolator_old.py
compecon/interpvec.py
compecon/lcpstep.py
compecon/linear.py
compecon/lqmodel.py
compecon/nonlinear.py
compecon/numbaclass.py
compecon/ocmodel.py
compecon/ode.py
compecon/optimize.py
compecon/quad.py
compecon/quadrature.py
compecon/smolyak.py
compecon/tools.py
compecon/demos/__init__.py
compecon/demos/dem01_basis.py
compecon/demos/demapp00.py
compecon/demos/demapp01.py
compecon/demos/demapp02.py
compecon/demos/demapp03.py
compecon/demos/demapp04.py
compecon/demos/demapp05.py
compecon/demos/demapp06.py
compecon/demos/demapp07.py
compecon/demos/demapp08.py
compecon/demos/demapp09.py
compecon/demos/demapp10.py
compecon/demos/demddp01.py
compecon/demos/demddp02.py
compecon/demos/demddp03.py
compecon/demos/demddp04.py
compecon/demos/demddp05.py
compecon/demos/demddp06.py
compecon/demos/demddp07.py
compecon/demos/demddp08.py
compecon/demos/demddp09.py
compecon/demos/demddp10.py
compecon/demos/demddp11.py
compecon/demos/demdif02.py
compecon/demos/demdp01.py
compecon/demos/demdp01a.py
compecon/demos/demdp01b.py
compecon/demos/demdp02.py
compecon/demos/demdp03.py
compecon/demos/demdp04.py
compecon/demos/demdp05.py
compecon/demos/demdp06.py
compecon/demos/demdp06borrar.py
compecon/demos/demdp07.py
compecon/demos/demdp08.py
compecon/demos/demdp09.py
compecon/demos/demdp10.py
compecon/demos/demdp11.py
compecon/demos/demdp12.py
compecon/demos/demintro01.py
compecon/demos/demintro02.py
compecon/demos/demlin01.py
compecon/demos/demlin02.py
compecon/demos/demlin03.py
compecon/demos/demmath01.py
compecon/demos/demmath02.py
compecon/demos/demmath06.py
compecon/demos/demopt01.py
compecon/demos/demopt04.py
compecon/demos/demopt05.py
compecon/demos/demopt06.py
compecon/demos/demopt07.py
compecon/demos/demopt08.py
compecon-2024.5.19.dist-info/LICENSE.txt
compecon-2024.5.19.dist-info/METADATA
compecon-2024.5.19.dist-info/WHEEL
compecon-2024.5.19.dist-info/top_level.txt
compecon-2024.5.19.dist-info/RECORD
