Metadata-Version: 2.1
Name: compecon
Version: 2024.5.19
Summary: A Computational Economics Toolbox
Home-page: http://randall-romero.com/code/compecon
Author: Randall Romero-Aguilar
Author-email: randall.romero@outlook.com
Project-URL: Bug Reports, https://github.com/randall-romero/CompEcon/issues
Project-URL: Source, https://github.com/randall-romero/CompEcon/
Keywords: computations economics numerical methods
Requires-Python: >=3.7
License-File: LICENSE.txt
Requires-Dist: numpy
Requires-Dist: scipy
Requires-Dist: matplotlib
Requires-Dist: seaborn
Requires-Dist: numba
Requires-Dist: nose
